commandify-0.0.4.10.dist-info/WHEEL
commandify-0.0.4.10.dist-info/top_level.txt
commandify-0.0.4.10.dist-info/METADATA
commandify-0.0.4.10.dist-info/pbr.json
commandify-0.0.4.10.dist-info/DESCRIPTION.rst
commandify-0.0.4.10.dist-info/RECORD
commandify-0.0.4.10.dist-info/metadata.json
commandify-0.0.4.10.data/scripts/commandify_examples
commandify/__init__.py
commandify/version.py
commandify/commandify_examples.py
commandify/commandify.py
