Metadata-Version: 2.0
Name: commandify
Version: 0.0.4.10
Summary: Simple command line commands through decorators
Home-page: https://github.com/markmuetz/commandify
Author: Mark Muetzelfeldt
Author-email: markmuetz@gmail.com
License: UNKNOWN
Keywords: command line argument arguments
Platform: UNKNOWN
Classifier: Development Status :: 3 - Alpha
Classifier: Environment :: Console
Classifier: License :: OSI Approved :: MIT License
Classifier: Natural Language :: English
Classifier: Operating System :: POSIX :: Linux
Classifier: Programming Language :: Python :: 2.7
